webtest_aiohttp.py
webtest_aiohttp-2.0.0.dist-info/DESCRIPTION.rst
webtest_aiohttp-2.0.0.dist-info/METADATA
webtest_aiohttp-2.0.0.dist-info/RECORD
webtest_aiohttp-2.0.0.dist-info/WHEEL
webtest_aiohttp-2.0.0.dist-info/metadata.json
webtest_aiohttp-2.0.0.dist-info/top_level.txt
