Metadata-Version: 2.0
Name: webtest-aiohttp
Version: 2.0.0
Summary: webtest-aiohttp provides integration of WebTest with aiohttp.web applications
Home-page: https://github.com/sloria/webtest-aiohttp
Author: Steven Loria
Author-email: sloria1@gmail.com
License: MIT
Keywords: webtest-aiohttp webtest aiohttp testing wsgi asyncio
Platform: UNKNOWN
Classifier: Intended Audience :: Developers
Classifier: Environment :: Web Environment
Classifier: License :: OSI Approved :: MIT License
Classifier: Natural Language :: English
Classifier: Programming Language :: Python :: 3
Classifier: Programming Language :: Python :: 3.4
Classifier: Programming Language :: Python :: 3.5
Classifier: Programming Language :: Python :: 3.6
Classifier: Topic :: Software Development :: Testing
Requires-Dist: webtest
